[
    {
        "scheduleId": 1001,
        "courseId": 1,
        "teacherId": "T9876",
        "classroomId": 1,
        "sectionId": 1,
        "weekDay": 1,
        "weeks": "1-16",
        "courseName": "计算机导论",
        "courseCode": "CS101",
        "teacherName": "张教授",
        "building": "教学楼A",
        "roomNumber": "A101",
        "startTime": "08:00:00",
        "endTime": "09:40:00",
        "credit": 3,
        "maxCapacity": 120,
        "enrolledCount": 118
    },
    {
        "scheduleId": 1002,
        "courseId": 2,
        "teacherId": "T1234",
        "classroomId": 2,
        "sectionId": 3,
        "weekDay": 2,
        "weeks": "1-8,10-16",
        "courseName": "数据结构",
        "courseCode": "CS201",
        "teacherName": "李老师",
        "building": "教学楼B",
        "roomNumber": "B202",
        "startTime": "10:00:00",
        "endTime": "11:40:00",
        "credit": 4,
        "maxCapacity": 80,
        "enrolledCount": 75
    },
    {
        "scheduleId": 1003,
        "courseId": 4,
        "teacherId": "T5432",
        "classroomId": 3,
        "sectionId": 5,
        "weekDay": 3,
        "weeks": "1-16",
        "courseName": "线性代数",
        "courseCode": "MA101",
        "teacherName": "王副教授",
        "building": "综合楼C",
        "roomNumber": "C301",
        "startTime": "14:00:00",
        "endTime": "15:40:00",
        "credit": 3,
        "maxCapacity": 150,
        "enrolledCount": 100
    },
    {
        "scheduleId": 1004,
        "courseId": 5,
        "teacherId": "T9876",
        "classroomId": 4,
        "sectionId": 7,
        "weekDay": 4,
        "weeks": "2-16/2",
        "courseName": "Web技术基础",
        "courseCode": "CS310",
        "teacherName": "张教授",
        "building": "实验楼D",
        "roomNumber": "D102",
        "startTime": "16:00:00",
        "endTime": "17:40:00",
        "credit": 2,
        "maxCapacity": 60,
        "enrolledCount": 60
    },
    {
        "scheduleId": 1005,
        "courseId": 6,
        "teacherId": "T1234",
        "classroomId": 10,
        "sectionId": 1,
        "weekDay": 5,
        "weeks": "1-16",
        "courseName": "大学物理",
        "courseCode": "PH101",
        "teacherName": "李老师",
        "building": "教学楼B",
        "roomNumber": "B101",
        "startTime": "08:00:00",
        "endTime": "09:40:00",
        "credit": 4,
        "maxCapacity": 100,
        "enrolledCount": 0
    }
]